{"header": [{"name": "obs", "title": "Origin", "size": 150, "sortable": true}, {"name": "ctp", "title": "Counterpart name", "size": 150, "sortable": true}, {"name": "ra", "title": "Right Ascension<br>[J2000]", "size": 50, "sortable": true}, {"name": "dec", "title": "Declination<br>[J2000]", "size": 50, "sortable": true}, {"name": "err", "title": "Positional error (90%)<br>[mas]", "size": 50, "sortable": true}], "data": [["IGR", "XTE J1543-568", 236.008, -56.712, 79200.003], ["Gaia", "Gaia DR3 5882543820303309696", 236.02206, -56.7617, 0.085], ["SAX", "XTE J1543-568", 235.982, -56.776, 125999.994], ["Swift", "2SXPS J154405.2-564541", 236.02203, -56.7614, 3500.0], ["2MASS", "2MASS J15440515-5645425", 236.02147, -56.7618, 60.0]]}